microcosm_fastapi/__init__.py
microcosm_fastapi/audit.py
microcosm_fastapi/context.py
microcosm_fastapi/errors.py
microcosm_fastapi/exception_handler.py
microcosm_fastapi/helpers.py
microcosm_fastapi/logging_data_map.py
microcosm_fastapi/metrics.py
microcosm_fastapi/namespaces.py
microcosm_fastapi/naming.py
microcosm_fastapi/operations.py
microcosm_fastapi/runserver.py
microcosm_fastapi/session.py
microcosm_fastapi/utils.py
microcosm_fastapi/conventions/__init__.py
microcosm_fastapi/conventions/crud.py
microcosm_fastapi/conventions/crud_adapter.py
microcosm_fastapi/conventions/parsers.py
microcosm_fastapi/conventions/schemas.py
microcosm_fastapi/conventions/build_info/__init__.py
microcosm_fastapi/conventions/build_info/models.py
microcosm_fastapi/conventions/build_info/resources.py
microcosm_fastapi/conventions/build_info/route.py
microcosm_fastapi/conventions/config/__init__.py
microcosm_fastapi/conventions/config/models.py
microcosm_fastapi/conventions/config/route.py
microcosm_fastapi/conventions/health/__init__.py
microcosm_fastapi/conventions/health/models.py
microcosm_fastapi/conventions/health/resources.py
microcosm_fastapi/conventions/health/route.py
microcosm_fastapi/conventions/landing/__init__.py
microcosm_fastapi/conventions/landing/route.py
microcosm_fastapi/database/__init__.py
microcosm_fastapi/database/health.py
microcosm_fastapi/database/postgres.py
microcosm_fastapi/database/session.py
microcosm_fastapi/database/store.py
microcosm_fastapi/database/encryption/__init__.py
microcosm_fastapi/database/encryption/store.py
microcosm_fastapi/docs/__init__.py
microcosm_fastapi/docs/static/redoc.standalone.js
microcosm_fastapi/docs/static/swagger-ui-bundle.js
microcosm_fastapi/docs/static/swagger-ui.css
microcosm_fastapi/encryption/__init__.py
microcosm_fastapi/encryption/crud_adapter.py
microcosm_fastapi/factories/__init__.py
microcosm_fastapi/factories/docs.py
microcosm_fastapi/factories/fastapi.py
microcosm_fastapi/pubsub/__init__.py
microcosm_fastapi-1.0.0.dist-info/METADATA
microcosm_fastapi-1.0.0.dist-info/WHEEL
microcosm_fastapi-1.0.0.dist-info/entry_points.txt
microcosm_fastapi-1.0.0.dist-info/top_level.txt
microcosm_fastapi-1.0.0.dist-info/RECORD
