Metadata-Version: 2.1
Name: microcosm-fastapi
Version: 1.0.0
Summary: Opinionated microservice API with FastAPI
Home-page: https://github.com/globality-corp//microcosm-fastapi
Author: Globality Engineering
Author-email: engineering@globality.com
Keywords: microcosm
Requires-Python: >=3.11
Requires-Dist: microcosm >=3.0.0
Requires-Dist: fastapi
Requires-Dist: uvicorn
Requires-Dist: aiofiles
Requires-Dist: SQLAlchemy[asyncio] >=1.4.0
Requires-Dist: httpx
Requires-Dist: h11 <0.13
Requires-Dist: click
Requires-Dist: jinja2
Requires-Dist: sqlalchemy-utils
Requires-Dist: microcosm-pubsub >=3.0.0
Requires-Dist: microcosm-postgres[encryption] >=4.0.0
Requires-Dist: asyncpg
Requires-Dist: psycopg2-binary >=2.7.5
Requires-Dist: makefun
Requires-Dist: pydantic <2.0.0
Requires-Dist: greenlet
Provides-Extra: lint
Requires-Dist: flake8 ; extra == 'lint'
Requires-Dist: flake8-print ; extra == 'lint'
Requires-Dist: flake8-isort ; extra == 'lint'
Provides-Extra: metrics
Requires-Dist: microcosm-metrics >=3.0.0 ; extra == 'metrics'
Provides-Extra: test
Requires-Dist: coverage >=3.7.1 ; extra == 'test'
Requires-Dist: PyHamcrest >=1.9.0 ; extra == 'test'
Requires-Dist: pytest ; extra == 'test'
Requires-Dist: pytest-cov ; extra == 'test'
Requires-Dist: pytest-asyncio ; extra == 'test'
Requires-Dist: microcosm-metrics >=3.0.0 ; extra == 'test'
Provides-Extra: typehinting
Requires-Dist: mypy ; extra == 'typehinting'
Requires-Dist: types-pkg-resources ; extra == 'typehinting'
Requires-Dist: types-requests ; extra == 'typehinting'
Requires-Dist: types-setuptools ; extra == 'typehinting'
